LICENSE
MANIFEST.in
README.rst
setup.py
fh_django_sendgrid_gae.egg-info/PKG-INFO
fh_django_sendgrid_gae.egg-info/SOURCES.txt
fh_django_sendgrid_gae.egg-info/dependency_links.txt
fh_django_sendgrid_gae.egg-info/requires.txt
fh_django_sendgrid_gae.egg-info/top_level.txt
sgbackend/__init__.py
sgbackend/mail.py
sgbackend/version.py