Metadata-Version: 1.0
Name: fh-django-sendgrid-gae
Version: 0.1.1
Summary: SendGrid Backend for Django on GAE using async task queues
Home-page: https://gitlab.com/futurehaus/django-sendgrid-gae
Author: Josh Turmel
Author-email: jt@futurehaus.com
License: MIT
Platform: UNKNOWN
